beacon/conf.py
beacon/scripts.py
beacon/version.py
beacon/acct/beacon/pg.py
beacon/acct/beacon/pika.py
beacon/acct/beacon/contracts/init.py
beacon/beacon/init.py
beacon/beacon/local.py
beacon/beacon/pg.py
beacon/beacon/pika.py
beacon/beacon/contracts/init.py
beacon/beacon/format/json.py
beacon/beacon/format/raw.py
beacon/beacon/format/contracts/init.py
pop_beacon-3.0.0.dist-info/LICENSE
pop_beacon-3.0.0.dist-info/METADATA
pop_beacon-3.0.0.dist-info/WHEEL
pop_beacon-3.0.0.dist-info/entry_points.txt
pop_beacon-3.0.0.dist-info/top_level.txt
pop_beacon-3.0.0.dist-info/RECORD
