Metadata-Version: 2.1
Name: pop-beacon
Version: 3.0.0
Summary: A system to continually watch interfaces for events and forward them respectively
Home-page: https://gitlab.com/saltstack/pop/beacon
Author: Tyler Johnson
Author-email: tyjohnson@vmware.com
License: UNKNOWN
Platform: UNKNOWN
Classifier: Environment :: Console
Classifier: Intended Audience :: Developers
Classifier: Intended Audience :: Information Technology
Classifier: Intended Audience :: System Administrators
Classifier: Operating System :: OS Independent
Classifier: Programming Language :: Python
Classifier: Programming Language :: Python :: 3.6
Classifier: Programming Language :: Python :: 3.7
Classifier: Programming Language :: Python :: 3.8
Classifier: Programming Language :: Python :: 3.9
Classifier: Development Status :: 5 - Production/Stable
Requires-Python: >=3.6
License-File: LICENSE
Requires-Dist: acct (>=5)
Requires-Dist: aio-pika
Requires-Dist: pop (>=16.3)
Requires-Dist: pop-evbus (>=3.0.0)
